character_range/__init__.py
character_range/intervals.py
character_range/maps.py
character_range/ranges.py
character_range-0.2.0.dist-info/LICENSE.txt
character_range-0.2.0.dist-info/METADATA
character_range-0.2.0.dist-info/WHEEL
character_range-0.2.0.dist-info/top_level.txt
character_range-0.2.0.dist-info/RECORD
