Metadata-Version: 2.1
Name: character-range
Version: 0.2.0
Summary: Generate string and bytes ranges
Author-email: InSyncWithFoo <insyncwithfoo@gmail.com>
License: MIT
Project-URL: Homepage, https://github.com/InSyncWithFoo/character-range
Project-URL: Documentation, https://character-range.readthedocs.io/
Keywords: char,character,range,byte,byte range
Classifier: Development Status :: 3 - Alpha
Classifier: Intended Audience :: Developers
Classifier: Topic :: Software Development :: Build Tools
Classifier: License :: OSI Approved :: The Unlicense (Unlicense)
Classifier: Programming Language :: Python :: 3
Classifier: Programming Language :: Python :: 3.10
Classifier: Programming Language :: Python :: 3.11
Classifier: Programming Language :: Python :: 3.12
Classifier: Programming Language :: Python :: 3 :: Only
Classifier: Typing :: Typed
Requires-Python: >=3.10
License-File: LICENSE.txt
Requires-Dist: typing-extensions ~=4.9.0
Provides-Extra: dev
Requires-Dist: build ~=1.0.3 ; extra == 'dev'
Requires-Dist: hypothesis ~=6.96.1 ; extra == 'dev'
Requires-Dist: mypy ~=1.8.0 ; extra == 'dev'
Requires-Dist: pyright ~=1.1.347 ; extra == 'dev'
Requires-Dist: pytest ~=7.4.3 ; extra == 'dev'
Requires-Dist: pytest-cov ~=4.1.0 ; extra == 'dev'
Requires-Dist: setuptools ~=69.0.2 ; extra == 'dev'
Requires-Dist: tox ~=4.12.1 ; extra == 'dev'
Requires-Dist: twine ~=4.0.2 ; extra == 'dev'
Requires-Dist: tzdata ~=2023.4 ; extra == 'dev'
Provides-Extra: docs
Requires-Dist: sphinx ~=7.2.6 ; extra == 'docs'
Requires-Dist: furo ~=2023.9.10 ; extra == 'docs'
